{
    "models": {
        "title": "zModels",
        "description": "Exclusive player models for SVIP",
        "equipped": "Equipped",
        "equip": "Equip",
        "unequip": "Unequip",
        "ct": "Counter Terrorist",
        "t": "Terrorist",
        "private": "Private",
        "search": "Search models...",
        "noResults": "No models found",
        "accessDenied": "SVIP access required to use this feature",
        "notLoggedIn": "Please log in to use this feature",
        "selectCategory": "Select category" 
    },
    "weapons": {
        "title": "zWeapons",
        "description": "Exclusive weapon skins for SVIP",
        "equipped": "Equipped",
        "equip": "Equip",
        "unequip": "Unequip",
        "search": "Search weapons...",
        "noResults": "No weapons found",
        "selectPack": "Select skin pack",
        "selectWeapon": "Select weapon type",
        "viewByType": "View by weapon type",
        "viewByPack": "View by skin pack",
        "accessDenied": "SVIP access required to use this feature",
        "notLoggedIn": "Please log in to use this feature",
        "categories": {
            "rifles": "Rifles",
            "pistols": "Pistols",
            "smgs": "SMGs",
            "heavy": "Heavy",
            "knives": "Knives",
            "grenades": "Grenades"
        }
    },
    "common": {
        "locked": "SVIP Required",
        "lockedDesc": "This feature is exclusive to SVIP users. Upgrade to unlock.",
        "loading": "Loading...",
        "equipSuccess": "Equipped successfully",
        "equipSuccessDesc": "Equipped {name}",
        "unequipSuccess": "Unequipped",
        "unequipSuccessDesc": "Removed {name}",
        "equipFailed": "Failed to equip",
        "unequipFailed": "Failed to unequip",
        "tooFast": "Too fast",
        "tooFastDesc": "Please wait before performing another action",
        "allWeapons": "All"
    },
    "mvp": {
        "title": "zMVP",
        "description": "Equip custom MVP anthems",
        "search": "Search MVP...",
        "noResults": "No MVP found",
        "free": "FREE",
        "vip": "VIP",
        "svip": "SVIP",
        "admin": "ADMIN",
        "preview": "Preview",
        "stop": "Stop",
        "apply": "Apply",
        "unequip": "Unequip",
        "equipped": "Equipped",
        "lockedVip": "VIP Required",
        "lockedVipDesc": "This feature is exclusive to VIP users.",
        "lockedSvip": "SVIP Required",
        "lockedSvipDesc": "This feature is exclusive to SVIP users. Upgrade to unlock."
    }
}
