{
    "title": "Skins",
    "description": "CS2 လက်နက်အရောင် များကို ရှာဖွေနှင့် စိတ်ကြိုက်ပြင်ဆင်ပါ",
    "tabs": {
        "weaponSkins": "လက်နက်အရောင်",
        "agents": "Agents",
        "musicKits": "Music Kits",
        "pinsCoins": "Pins & Coins"
    },
    "categories": {
        "gloves": "လက်အိတ်",
        "rifles": "Rifles",
        "knives": "ဓားများ", 
        "smgs": "SMGs",
        "pistols": "Pistols",
        "heavy": "Heavy",
        "equipment": "ပစ္စည်းကိရိယာ"
    },
    "team": {
        "both": "အသင်းနှစ်ဖက်",
        "ct": "CT ဘက်",
        "t": "T ဘက်"
    },
    "search": "Skin ရှာဖွေ...",
    "noResults": "Skin မတွေ့ပါ",
    "selectWeapon": "Skin များကြည့်ရန် လက်နက် ရွေးချယ်ပါ",
    "loginRequired": "Skins အသုံးပြုရန် ဝင်ရောက်ပါ",
    "loading": "Skin များ ဖွင့်နေသည်...",
    "itemCount": "{count} ခု",
    "toast": {
        "tooFast": "အလွန်မြန်သည်!",
        "tooFastDesc": "ထပ်စမ်းကြည့်မီ ၂ စက္ကန့် စောင့်ပါ",
        "equipped": "တပ်ဆင်ပြီး!",
        "equippedDesc": "{name} အောင်မြင်စွာ တပ်ဆင်ပြီး",
        "unequipped": "ဖြုတ်ပြီး!",
        "unequippedDesc": "{name} ဖယ်ရှားပြီး",
        "equipFailed": "တပ်ဆင်၍ မရပါ",
        "unequipFailed": "ဖြုတ်၍ မရပါ",
        "unknownError": "မသိသော အမှား"
    }
}
