{
    "nav": {
        "home": "Home",
        "dashboard": "Dashboard",
        "account": "Account",
        "security": "Seguridad",
        "settings": "Mga Setting",
        "servers": "Mga Server",
        "bans": "Mga Ban",
        "mutes": "Mga Mute / Gag",
        "skins": "Mga Skin",
        "skinCollections": "Mga Koleksyon",
        "zmodels": "zModels",
        "zweapons": "zWeapons",
        "rankings": "Mga Ranggo",
        "battleMode": "Battle Mode",
        "admin": "Admin Panel",
        "login": "Login",
        "register": "Magrehistro",
        "logout": "Mag-logout",
        "support": "Suporta"
    },
    "actions": {
        "copy": "Kopyahin",
        "connect": "Kumonekta",
        "save": "I-save",
        "cancel": "Kanselahin",
        "close": "Isara",
        "confirm": "Kumpirmahin",
        "delete": "Tanggalin",
        "edit": "I-edit",
        "back": "Bumalik",
        "retry": "Subukang muli",
        "search": "Maghanap..."
    },
    "status": {
        "online": "Online",
        "offline": "Offline",
        "loading": "Naglo-load...",
        "error": "Error",
        "success": "Tagumpay"
    },
    "toast": {
        "copied": "Nakopya sa clipboard",
        "copyFailed": "Nabigong kopyahin"
    },
    "footer": {
        "rights": "Lahat ng karapatan ay nakalaan"
    },
    "sidebar": {
        "collapse": "I-collapse",
        "expand": "I-expand",
        "language": "Wika",
        "theme": "Tema",
        "terms": "Mga Tuntunin at Privacy",
        "guest": "Bisita",
        "settings": "Mga Setting"
    },
    "announcement": {
        "title": "Anunsyo ng System",
        "sourceLink": "Tingnan ang orihinal na post"
    },
    "errors": {
        "notFound": {
            "title": "404",
            "message": "Ang page na hinahanap mo ay hindi umiiral",
            "home": "Home",
            "back": "Bumalik"
        },
        "serverError": {
            "title": "500",
            "message": "May naganap na hindi inaasahang error",
            "errorCode": "Error code: {code}",
            "pleaseRetry": "Subukang muli",
            "retry": "Ulitin",
            "home": "Home"
        }
    },
    "forcePasswordChange": {
        "title": "Kailangang Palitan ang Password",
        "description": "Kinakailangan ng administrator na palitan mo ang iyong password para sa seguridad. Kailangan mo itong palitan bago magpatuloy.",
        "newPassword": "Bagong Password",
        "confirmPassword": "Kumpirmahin ang Password",
        "submit": "Palitan ang Password",
        "rules": {
            "minLength": "Hindi bababa sa 8 karakter",
            "uppercase": "Hindi bababa sa 1 malaking letra",
            "number": "Hindi bababa sa 1 numero",
            "match": "Dapat magtugma ang mga password"
        }
    },
    "welcomePopup": {
        "greeting_night": "Magandang gabi, {name}",
        "greeting_morning": "Magandang umaga, {name}",
        "greeting_noon": "Magandang tanghali, {name}",
        "greeting_afternoon": "Magandang hapon, {name}",
        "greeting_evening": "Magandang gabi, {name}",
        "guest": "Bisita",
        "warning": "Ang paglalaro ng higit sa 180 minuto/araw ay maaaring makaapekto sa kalusugan"
    }
}