{
    "hero": {
        "explore": "ស្វែងរក",
        "store": "ហាង",
        "letsPlayNow": "មកលេងឥឡូវ!",
        "wantToBeVip": "ចង់ជា VIP?",
        "loginToZsystems": "ចូល zSystems",
        "weaponSkins": "Skin អាវុធ",
        "ranks": "ចំណាត់ថ្នាក់",
        "contact": "ទំនាក់ទំនង",
        "getDemo": "ទទួល Demo", 
        "subbrand": "zSYSTEMS-v2",
        "playNow": "លេងឥឡូវ",
        "login": "ចូល",
        "changeSkins": "ប្តូរ Skin អាវុធ"
    },
    "nav": {
        "community": "សហគមន៍",
        "ranks": "ចំណាត់ថ្នាក់",
        "support": "ជំនួយ"
    },
    "stats": {
        "uptime": "UPTIME",
        "ping": "PING",
        "players6h": "អ្នកលេង / ៦ម"
    },
    "footer": {
        "selectLanguage": "ជ្រើសរើសភាសា",
        "language": "ភាសាខ្មែរ",
        "privacy": "គោលការណ៍ភាពឯកជន",
        "terms": "លក្ខខណ្ឌសេវាកម្ម",
        "contact": "ទំនាក់ទំនង",
        "poweredBy": "ដំណើរការដោយ zSystems — អភិវឌ្ឍដោយ zhw1nq & 7-Mau TEAM",
        "match": {
    "title": "ការប្រកួត",
    "subtitle": "ប្រវត្តិនៃការប្រកួតនៅលើប្រព័ន្ធ",
    "searchPlaceholder": "ស្វែងរកតាមឈ្មោះក្រុម...",
    "noMatches": "រកមិនឃើញការប្រកួតណាមួយទេ",
    "live": "កំពុងប្រកួត",
    "finished": "បានបញ្ចប់",
    "win": "ឈ្នះ",
    "lose": "ចាញ់",
    "draw": "ស្មើ",
    "duration": "{minutes} នាទី",
    "server": "ម៉ាស៊ីនមេ",
    "downloadDemo": "ទាញយក Demo",
    "noDemo": "មិនទាន់មាន Demo",
    "viewDetail": "ព័ត៌មានលម្អិត",
    "backToList": "ត្រឡប់ក្រោយ",
    "matchNumber": "ការប្រកួត #{id}",
    "map": "ផែនទី",
    "records": "{count} ការប្រកួត",
    "page": "ទំព័រ {page}/{total}",
    "previous": "មុន",
    "next": "បន្ទាប់",
    "tabs": {
        "scoreboard": "តារាងពិន្ទុ",
        "rounds": "ព្រឹត្តិការណ៍",
        "kills": "ការសម្លាប់",
        "roundStats": "ស្ថិតិតាម Round",
        "economy": "សេដ្ឋកិច្ច"
    },
    "scoreboard": {
        "player": "អ្នកលេង",
        "kills": "K",
        "deaths": "D",
        "assists": "A",
        "adr": "ADR",
        "hsPercent": "HS%",
        "kd": "K/D",
        "damage": "DMG",
        "entry": "Entry",
        "entryWins": "Entry W",
        "utilityDmg": "Utility DMG",
        "flash": "Flash",
        "clutch1v1": "1v1",
        "clutch1v2": "1v2",
        "firstKills": "FK",
        "accuracy": "ភាពត្រឹមត្រូវ",
        "ace": "Ace",
        "quadKill": "4K",
        "tripleKill": "3K",
        "doubleKill": "2K",
        "liveTime": "ពេលវេលារស់",
        "cashEarned": "ប្រាក់រកបាន"
    },
    "rounds": {
        "round": "R{number}",
        "half1": "តង់ទី 1",
        "half2": "តង់ទី 2",
        "overtime": "ម៉ោងបន្ថែម",
        "bombExploded": "គ្រាប់បែកផ្ទុះ",
        "bombDefused": "ដោះគ្រាប់បែក",
        "elimination": "កម្ចាត់",
        "timeout": "អស់ពេល",
        "drawRound": "ស្មើ",
        "mvp": "MVP",
        "planted": "ដាក់គ្រាប់បែក",
        "defused": "ដោះគ្រាប់បែក"
    },
    "kills": {
        "round": "Round",
        "killer": "អ្នកបាញ់",
        "victim": "អ្នករងគ្រោះ",
        "weapon": "អាវុធ",
        "distance": "ចម្ងាយ",
        "assister": "ជំនួយ",
        "headshot": "HS",
        "wallbang": "WB",
        "noscope": "NS",
        "thrusmoke": "Smoke",
        "blind": "Blind",
        "inAir": "Air",
        "flashAssist": "Flash",
        "allRounds": "ទាំងអស់",
        "filterByRound": "តម្រងតាម Round",
        "entry": "Entry"
    },
    "roundStats": {
        "round": "Round",
        "player": "អ្នកលេង",
        "side": "ក្រុម",
        "kills": "K",
        "deaths": "D",
        "assists": "A",
        "damage": "DMG",
        "hsKills": "HS",
        "utilDmg": "Util",
        "flash": "Flash",
        "trade": "Trade",
        "alive": "រស់",
        "dead": "ស្លាប់",
        "selectRound": "ជ្រើសរើស Round"
    },
    "economy": {
        "avgEquipValue": "មធ្យមភាគសម្ភារៈ",
        "totalMoney": "ចំណាយសរុប",
        "round": "Round",
        "team": "ក្រុម",
        "equipValue": "សម្ភារៈ",
        "moneyLeft": "ប្រាក់នៅសល់",
        "weapon": "អាវុធចម្បង",
        "armor": "អាវការពារ",
        "helmet": "មួក",
        "defuser": "Kit",
        "grenades": "គ្រាប់បែកដៃ",
        "fullBuy": "Full Buy",
        "forceBuy": "Force Buy",
        "eco": "Eco",
        "pistol": "Pistol"
    }
}
    }
}
